<?xml version="1.0" encoding="UTF-8"?>
<!DOCTYPE mapper PUBLIC "-//mybatis.org//DTD Mapper 3.0//EN" "http://mybatis.org/dtd/mybatis-3-mapper.dtd">
<mapper namespace="com.android.app.dao.DynamicTableMapper">
  <resultMap id="BaseResultMap" type="com.android.app.entity.DynamicTable">
    <!--
      WARNING - @mbg.generated
      This element is automatically generated by MyBatis Generator, do not modify.
    -->
    <id column="id" jdbcType="INTEGER" property="id" />
    <result column="dy_id" jdbcType="BIGINT" property="dyId" />
    <result column="dy_title" jdbcType="VARCHAR" property="dyTitle" />
    <result column="dy_type" jdbcType="INTEGER" property="dyType" />
    <result column="u_id" jdbcType="INTEGER" property="uId" />
    <result column="read_count" jdbcType="INTEGER" property="readCount" />
    <result column="gmt_create" jdbcType="TIMESTAMP" property="gmtCreate" />
    <result column="gmt_update" jdbcType="TIMESTAMP" property="gmtUpdate" />
  </resultMap>
  <resultMap extends="BaseResultMap" id="ResultMapWithBLOBs" type="com.android.app.entity.DynamicTable">
    <!--
      WARNING - @mbg.generated
      This element is automatically generated by MyBatis Generator, do not modify.
    -->
    <result column="dy_text" jdbcType="LONGVARCHAR" property="dyText" />
  </resultMap>
  <sql id="Example_Where_Clause">
    <!--
      WARNING - @mbg.generated
      This element is automatically generated by MyBatis Generator, do not modify.
    -->
    <where>
      <foreach collection="oredCriteria" item="criteria" separator="or">
        <if test="criteria.valid">
          <trim prefix="(" prefixOverrides="and" suffix=")">
            <foreach collection="criteria.criteria" item="criterion">
              <choose>
                <when test="criterion.noValue">
                  and ${criterion.condition}
                </when>
                <when test="criterion.singleValue">
                  and ${criterion.condition} #{criterion.value}
                </when>
                <when test="criterion.betweenValue">
                  and ${criterion.condition} #{criterion.value} and #{criterion.secondValue}
                </when>
                <when test="criterion.listValue">
                  and ${criterion.condition}
                  <foreach close=")" collection="criterion.value" item="listItem" open="(" separator=",">
                    #{listItem}
                  </foreach>
                </when>
              </choose>
            </foreach>
          </trim>
        </if>
      </foreach>
    </where>
  </sql>
  <sql id="Update_By_Example_Where_Clause">
    <!--
      WARNING - @mbg.generated
      This element is automatically generated by MyBatis Generator, do not modify.
    -->
    <where>
      <foreach collection="example.oredCriteria" item="criteria" separator="or">
        <if test="criteria.valid">
          <trim prefix="(" prefixOverrides="and" suffix=")">
            <foreach collection="criteria.criteria" item="criterion">
              <choose>
                <when test="criterion.noValue">
                  and ${criterion.condition}
                </when>
                <when test="criterion.singleValue">
                  and ${criterion.condition} #{criterion.value}
                </when>
                <when test="criterion.betweenValue">
                  and ${criterion.condition} #{criterion.value} and #{criterion.secondValue}
                </when>
                <when test="criterion.listValue">
                  and ${criterion.condition}
                  <foreach close=")" collection="criterion.value" item="listItem" open="(" separator=",">
                    #{listItem}
                  </foreach>
                </when>
              </choose>
            </foreach>
          </trim>
        </if>
      </foreach>
    </where>
  </sql>
  <sql id="Base_Column_List">
    <!--
      WARNING - @mbg.generated
      This element is automatically generated by MyBatis Generator, do not modify.
    -->
    id, dy_id, dy_title, dy_type, u_id, read_count, gmt_create, gmt_update
  </sql>
  <sql id="Blob_Column_List">
    <!--
      WARNING - @mbg.generated
      This element is automatically generated by MyBatis Generator, do not modify.
    -->
    dy_text
  </sql>
  <select id="selectByExampleWithBLOBs" parameterType="com.android.app.entity.DynamicTableExample" resultMap="ResultMapWithBLOBs">
    <!--
      WARNING - @mbg.generated
      This element is automatically generated by MyBatis Generator, do not modify.
    -->
    select
    <if test="distinct">
      distinct
    </if>
    <include refid="Base_Column_List" />
    ,
    <include refid="Blob_Column_List" />
    from dynamic_table
    <if test="_parameter != null">
      <include refid="Example_Where_Clause" />
    </if>
    <if test="orderByClause != null">
      order by ${orderByClause}
    </if>
  </select>
  <select id="selectByExample" parameterType="com.android.app.entity.DynamicTableExample" resultMap="BaseResultMap">
    <!--
      WARNING - @mbg.generated
      This element is automatically generated by MyBatis Generator, do not modify.
    -->
    select
    <if test="distinct">
      distinct
    </if>
    <include refid="Base_Column_List" />
    from dynamic_table
    <if test="_parameter != null">
      <include refid="Example_Where_Clause" />
    </if>
    <if test="orderByClause != null">
      order by ${orderByClause}
    </if>
  </select>
  <select id="selectByPrimaryKey" parameterType="java.lang.Integer" resultMap="ResultMapWithBLOBs">
    <!--
      WARNING - @mbg.generated
      This element is automatically generated by MyBatis Generator, do not modify.
    -->
    select 
    <include refid="Base_Column_List" />
    ,
    <include refid="Blob_Column_List" />
    from dynamic_table
    where id = #{id,jdbcType=INTEGER}
  </select>
  <delete id="deleteByPrimaryKey" parameterType="java.lang.Integer">
    <!--
      WARNING - @mbg.generated
      This element is automatically generated by MyBatis Generator, do not modify.
    -->
    delete from dynamic_table
    where id = #{id,jdbcType=INTEGER}
  </delete>
  <delete id="deleteByExample" parameterType="com.android.app.entity.DynamicTableExample">
    <!--
      WARNING - @mbg.generated
      This element is automatically generated by MyBatis Generator, do not modify.
    -->
    delete from dynamic_table
    <if test="_parameter != null">
      <include refid="Example_Where_Clause" />
    </if>
  </delete>
  <insert id="insert" parameterType="com.android.app.entity.DynamicTable">
    <!--
      WARNING - @mbg.generated
      This element is automatically generated by MyBatis Generator, do not modify.
    -->
    insert into dynamic_table (id, dy_id, dy_title, 
      dy_type, u_id, read_count, 
      gmt_create, gmt_update, dy_text
      )
    values (#{id,jdbcType=INTEGER}, #{dyId,jdbcType=BIGINT}, #{dyTitle,jdbcType=VARCHAR}, 
      #{dyType,jdbcType=INTEGER}, #{uId,jdbcType=INTEGER}, #{readCount,jdbcType=INTEGER}, 
      #{gmtCreate,jdbcType=TIMESTAMP}, #{gmtUpdate,jdbcType=TIMESTAMP}, #{dyText,jdbcType=LONGVARCHAR}
      )
  </insert>
  <insert id="insertSelective" parameterType="com.android.app.entity.DynamicTable">
    <!--
      WARNING - @mbg.generated
      This element is automatically generated by MyBatis Generator, do not modify.
    -->
    insert into dynamic_table
    <trim prefix="(" suffix=")" suffixOverrides=",">
      <if test="id != null">
        id,
      </if>
      <if test="dyId != null">
        dy_id,
      </if>
      <if test="dyTitle != null">
        dy_title,
      </if>
      <if test="dyType != null">
        dy_type,
      </if>
      <if test="uId != null">
        u_id,
      </if>
      <if test="readCount != null">
        read_count,
      </if>
      <if test="gmtCreate != null">
        gmt_create,
      </if>
      <if test="gmtUpdate != null">
        gmt_update,
      </if>
      <if test="dyText != null">
        dy_text,
      </if>
    </trim>
    <trim prefix="values (" suffix=")" suffixOverrides=",">
      <if test="id != null">
        #{id,jdbcType=INTEGER},
      </if>
      <if test="dyId != null">
        #{dyId,jdbcType=BIGINT},
      </if>
      <if test="dyTitle != null">
        #{dyTitle,jdbcType=VARCHAR},
      </if>
      <if test="dyType != null">
        #{dyType,jdbcType=INTEGER},
      </if>
      <if test="uId != null">
        #{uId,jdbcType=INTEGER},
      </if>
      <if test="readCount != null">
        #{readCount,jdbcType=INTEGER},
      </if>
      <if test="gmtCreate != null">
        #{gmtCreate,jdbcType=TIMESTAMP},
      </if>
      <if test="gmtUpdate != null">
        #{gmtUpdate,jdbcType=TIMESTAMP},
      </if>
      <if test="dyText != null">
        #{dyText,jdbcType=LONGVARCHAR},
      </if>
    </trim>
  </insert>
  <select id="countByExample" parameterType="com.android.app.entity.DynamicTableExample" resultType="java.lang.Long">
    <!--
      WARNING - @mbg.generated
      This element is automatically generated by MyBatis Generator, do not modify.
    -->
    select count(*) from dynamic_table
    <if test="_parameter != null">
      <include refid="Example_Where_Clause" />
    </if>
  </select>
  <update id="updateByExampleSelective" parameterType="map">
    <!--
      WARNING - @mbg.generated
      This element is automatically generated by MyBatis Generator, do not modify.
    -->
    update dynamic_table
    <set>
      <if test="record.id != null">
        id = #{record.id,jdbcType=INTEGER},
      </if>
      <if test="record.dyId != null">
        dy_id = #{record.dyId,jdbcType=BIGINT},
      </if>
      <if test="record.dyTitle != null">
        dy_title = #{record.dyTitle,jdbcType=VARCHAR},
      </if>
      <if test="record.dyType != null">
        dy_type = #{record.dyType,jdbcType=INTEGER},
      </if>
      <if test="record.uId != null">
        u_id = #{record.uId,jdbcType=INTEGER},
      </if>
      <if test="record.readCount != null">
        read_count = #{record.readCount,jdbcType=INTEGER},
      </if>
      <if test="record.gmtCreate != null">
        gmt_create = #{record.gmtCreate,jdbcType=TIMESTAMP},
      </if>
      <if test="record.gmtUpdate != null">
        gmt_update = #{record.gmtUpdate,jdbcType=TIMESTAMP},
      </if>
      <if test="record.dyText != null">
        dy_text = #{record.dyText,jdbcType=LONGVARCHAR},
      </if>
    </set>
    <if test="_parameter != null">
      <include refid="Update_By_Example_Where_Clause" />
    </if>
  </update>
  <update id="updateByExampleWithBLOBs" parameterType="map">
    <!--
      WARNING - @mbg.generated
      This element is automatically generated by MyBatis Generator, do not modify.
    -->
    update dynamic_table
    set id = #{record.id,jdbcType=INTEGER},
      dy_id = #{record.dyId,jdbcType=BIGINT},
      dy_title = #{record.dyTitle,jdbcType=VARCHAR},
      dy_type = #{record.dyType,jdbcType=INTEGER},
      u_id = #{record.uId,jdbcType=INTEGER},
      read_count = #{record.readCount,jdbcType=INTEGER},
      gmt_create = #{record.gmtCreate,jdbcType=TIMESTAMP},
      gmt_update = #{record.gmtUpdate,jdbcType=TIMESTAMP},
      dy_text = #{record.dyText,jdbcType=LONGVARCHAR}
    <if test="_parameter != null">
      <include refid="Update_By_Example_Where_Clause" />
    </if>
  </update>
  <update id="updateByExample" parameterType="map">
    <!--
      WARNING - @mbg.generated
      This element is automatically generated by MyBatis Generator, do not modify.
    -->
    update dynamic_table
    set id = #{record.id,jdbcType=INTEGER},
      dy_id = #{record.dyId,jdbcType=BIGINT},
      dy_title = #{record.dyTitle,jdbcType=VARCHAR},
      dy_type = #{record.dyType,jdbcType=INTEGER},
      u_id = #{record.uId,jdbcType=INTEGER},
      read_count = #{record.readCount,jdbcType=INTEGER},
      gmt_create = #{record.gmtCreate,jdbcType=TIMESTAMP},
      gmt_update = #{record.gmtUpdate,jdbcType=TIMESTAMP}
    <if test="_parameter != null">
      <include refid="Update_By_Example_Where_Clause" />
    </if>
  </update>
  <update id="updateByPrimaryKeySelective" parameterType="com.android.app.entity.DynamicTable">
    <!--
      WARNING - @mbg.generated
      This element is automatically generated by MyBatis Generator, do not modify.
    -->
    update dynamic_table
    <set>
      <if test="dyId != null">
        dy_id = #{dyId,jdbcType=BIGINT},
      </if>
      <if test="dyTitle != null">
        dy_title = #{dyTitle,jdbcType=VARCHAR},
      </if>
      <if test="dyType != null">
        dy_type = #{dyType,jdbcType=INTEGER},
      </if>
      <if test="uId != null">
        u_id = #{uId,jdbcType=INTEGER},
      </if>
      <if test="readCount != null">
        read_count = #{readCount,jdbcType=INTEGER},
      </if>
      <if test="gmtCreate != null">
        gmt_create = #{gmtCreate,jdbcType=TIMESTAMP},
      </if>
      <if test="gmtUpdate != null">
        gmt_update = #{gmtUpdate,jdbcType=TIMESTAMP},
      </if>
      <if test="dyText != null">
        dy_text = #{dyText,jdbcType=LONGVARCHAR},
      </if>
    </set>
    where id = #{id,jdbcType=INTEGER}
  </update>
  <update id="updateByPrimaryKeyWithBLOBs" parameterType="com.android.app.entity.DynamicTable">
    <!--
      WARNING - @mbg.generated
      This element is automatically generated by MyBatis Generator, do not modify.
    -->
    update dynamic_table
    set dy_id = #{dyId,jdbcType=BIGINT},
      dy_title = #{dyTitle,jdbcType=VARCHAR},
      dy_type = #{dyType,jdbcType=INTEGER},
      u_id = #{uId,jdbcType=INTEGER},
      read_count = #{readCount,jdbcType=INTEGER},
      gmt_create = #{gmtCreate,jdbcType=TIMESTAMP},
      gmt_update = #{gmtUpdate,jdbcType=TIMESTAMP},
      dy_text = #{dyText,jdbcType=LONGVARCHAR}
    where id = #{id,jdbcType=INTEGER}
  </update>
  <update id="updateByPrimaryKey" parameterType="com.android.app.entity.DynamicTable">
    <!--
      WARNING - @mbg.generated
      This element is automatically generated by MyBatis Generator, do not modify.
    -->
    update dynamic_table
    set dy_id = #{dyId,jdbcType=BIGINT},
      dy_title = #{dyTitle,jdbcType=VARCHAR},
      dy_type = #{dyType,jdbcType=INTEGER},
      u_id = #{uId,jdbcType=INTEGER},
      read_count = #{readCount,jdbcType=INTEGER},
      gmt_create = #{gmtCreate,jdbcType=TIMESTAMP},
      gmt_update = #{gmtUpdate,jdbcType=TIMESTAMP}
    where id = #{id,jdbcType=INTEGER}
  </update>
</mapper>